odoo/addons/connector_jira_servicedesk/README.rst
odoo/addons/connector_jira_servicedesk/__init__.py
odoo/addons/connector_jira_servicedesk/__manifest__.py
odoo/addons/connector_jira_servicedesk/i18n/connector_jira_servicedesk.pot
odoo/addons/connector_jira_servicedesk/models/__init__.py
odoo/addons/connector_jira_servicedesk/models/account_analytic_line/__init__.py
odoo/addons/connector_jira_servicedesk/models/account_analytic_line/common.py
odoo/addons/connector_jira_servicedesk/models/account_analytic_line/importer.py
odoo/addons/connector_jira_servicedesk/models/jira_backend/__init__.py
odoo/addons/connector_jira_servicedesk/models/jira_backend/common.py
odoo/addons/connector_jira_servicedesk/models/jira_organization/__init__.py
odoo/addons/connector_jira_servicedesk/models/jira_organization/adapter.py
odoo/addons/connector_jira_servicedesk/models/jira_organization/common.py
odoo/addons/connector_jira_servicedesk/models/jira_organization/importer.py
odoo/addons/connector_jira_servicedesk/models/project_project/__init__.py
odoo/addons/connector_jira_servicedesk/models/project_project/binder.py
odoo/addons/connector_jira_servicedesk/models/project_project/common.py
odoo/addons/connector_jira_servicedesk/models/project_project/project_link_jira.py
odoo/addons/connector_jira_servicedesk/models/project_task/__init__.py
odoo/addons/connector_jira_servicedesk/models/project_task/importer.py
odoo/addons/connector_jira_servicedesk/readme/CONTRIBUTORS.rst
odoo/addons/connector_jira_servicedesk/readme/DESCRIPTION.rst
odoo/addons/connector_jira_servicedesk/readme/USAGE.rst
odoo/addons/connector_jira_servicedesk/security/ir.model.access.csv
odoo/addons/connector_jira_servicedesk/static/description/icon.png
odoo/addons/connector_jira_servicedesk/static/description/index.html
odoo/addons/connector_jira_servicedesk/tests/__init__.py
odoo/addons/connector_jira_servicedesk/tests/common.py
odoo/addons/connector_jira_servicedesk/tests/test_import_organization.py
odoo_addon_connector_jira_servicedesk-15.0.1.0.0.3.dist-info/METADATA
odoo_addon_connector_jira_servicedesk-15.0.1.0.0.3.dist-info/WHEEL
odoo_addon_connector_jira_servicedesk-15.0.1.0.0.3.dist-info/top_level.txt
odoo_addon_connector_jira_servicedesk-15.0.1.0.0.3.dist-info/RECORD
